9/four.v
module four(I, S, f);
	input [7:0]I;
	input [2:0]S;
	wire [7:0]Y;
	output reg f;
	decoder3t8 D0(1'b1, S, Y);
	integer k;
	always @(*)
	begin
		f=0;
		for(k=0; k<=7; k=k+1)
			f=f|(I[k]&Y[k]);
	end
endmodule


module decoder3t8(En, W, Y);
	input [2:0]W;
	input En;
	output reg [7:0]Y; 
	integer k;
	always @(*)
	begin
		Y=8'b00000000;
		for (k = 0; k <= 7; k = k+1)
			if ((W == k) && (En == 1))
				Y[k] = 1;   			 
	end
endmodule

9/four_tb.v
`include "four.v"

module four_tb();
reg [2:0]S;
reg [7:0]I;
wire f;

four ex(I,S,f);
initial
begin
	$dumpfile("four_tb.vcd");
	$dumpvars(0,four_tb);
	
	I=8'b00110010;
	S=3'b000; #20;
	S=3'b001; #20;
	S=3'b010; #20;
	S=3'b011; #20;
	S=3'b100; #20;
	S=3'b101; #20;
	S=3'b110; #20;
	S=3'b111; #20;
		
	$display("test Complete");
end
endmodule

9/four_tb.vcd
$date
	Thu Oct 27 09:59:57 2022
$end
$version
	Icarus Verilog
$end
$timescale
	1s
$end
$scope module four_tb $end
$var wire 1 ! f $end
$var reg 8 " I [7:0] $end
$var reg 3 # S [2:0] $end
$scope module ex $end
$var wire 8 $ I [7:0] $end
$var wire 3 % S [2:0] $end
$var wire 8 & Y [7:0] $end
$var reg 1 ! f $end
$var integer 32 ' k [31:0] $end
$scope module D0 $end
$var wire 1 ( En $end
$var wire 3 ) W [2:0] $end
$var reg 8 * Y [7:0] $end
$var integer 32 + k [31:0] $end
$upscope $end
$upscope $end
$upscope $end
$enddefinitions $end
#0
$dumpvars
b1000 +
b1 *
b0 )
1(
b1000 '
b1 &
b0 %
b110010 $
b0 #
b110010 "
0!
$end
#20
1!
b1000 '
b1000 +
b10 &
b10 *
b1 #
b1 %
b1 )
#40
b1000 '
0!
b1000 +
b100 &
b100 *
b10 #
b10 %
b10 )
#60
b1000 '
b1000 +
b1000 &
b1000 *
b11 #
b11 %
b11 )
#80
1!
b1000 '
b1000 +
b10000 &
b10000 *
b100 #
b100 %
b100 )
#100
b1000 '
1!
b1000 +
b100000 &
b100000 *
b101 #
b101 %
b101 )
#120
b1000 '
0!
b1000 +
b1000000 &
b1000000 *
b110 #
b110 %
b110 )
#140
b1000 '
b1000 +
b10000000 &
b10000000 *
b111 #
b111 %
b111 )
