9/one.v
module one(En, W, f);
	input [3:0]W;
	input En;
	output f;
	wire [0:15]Y;
	decoder4t16 D(En, W,Y);
	assign f=Y[1] | Y[3] | Y[6] | Y[7] | Y[9] | Y[14] | Y[15];
endmodule

module decoder4t16(En, W, Y);
	input [3:0]W;
	input En;
	output reg [0:15]Y; 
	integer k;
	always @(*)
	begin
		Y=16'b0000000000000000;
		for (k = 0; k <= 15; k = k+1)
			if ((W == k) && (En == 1))
				Y[k] = 1;   			 
	end
endmodule

9/one_tb.v
`timescale 1ns/1ns
`include "one.v"

module one_tb();
reg [3:0]W;
reg En;
wire f;

one ex(En, W, f);
initial
begin
	$dumpfile("one_tb.vcd");
	$dumpvars(0,one_tb);
	
	En=1'b1;
	W=4'b0000; #20;
	W=4'b0001; #20;
	W=4'b0010; #20;
	W=4'b0011; #20;
	W=4'b0100; #20;
	W=4'b0101; #20;
	W=4'b0110; #20;
	W=4'b0111; #20;
	W=4'b1000; #20;
	W=4'b1001; #20;
	W=4'b1010; #20;
	W=4'b1011; #20;
	W=4'b1100; #20;
	W=4'b1101; #20;
	W=4'b1110; #20;
	W=4'b1111; #20;

	$display("test Complete");
end
endmodule

9/one_tb.vcd
$date
	Thu Oct 27 09:18:32 2022
$end
$version
	Icarus Verilog
$end
$timescale
	1ns
$end
$scope module one_tb $end
$var wire 1 ! f $end
$var reg 1 " En $end
$var reg 4 # W [3:0] $end
$scope module ex $end
$var wire 1 " En $end
$var wire 4 $ W [3:0] $end
$var wire 1 ! f $end
$var wire 16 % Y [0:15] $end
$scope module D $end
$var wire 1 " En $end
$var wire 4 & W [3:0] $end
$var reg 16 ' Y [0:15] $end
$var integer 32 ( k [31:0] $end
$upscope $end
$upscope $end
$upscope $end
$enddefinitions $end
#0
$dumpvars
b10000 (
b1000000000000000 '
b0 &
b1000000000000000 %
b0 $
b0 #
1"
0!
$end
#20
1!
b10000 (
b100000000000000 %
b100000000000000 '
b1 #
b1 $
b1 &
#40
0!
b10000 (
b10000000000000 %
b10000000000000 '
b10 #
b10 $
b10 &
#60
1!
b10000 (
b1000000000000 %
b1000000000000 '
b11 #
b11 $
b11 &
#80
0!
b10000 (
b100000000000 %
b100000000000 '
b100 #
b100 $
b100 &
#100
b10000 (
b10000000000 %
b10000000000 '
b101 #
b101 $
b101 &
#120
1!
b10000 (
b1000000000 %
b1000000000 '
b110 #
b110 $
b110 &
#140
b10000 (
b100000000 %
b100000000 '
b111 #
b111 $
b111 &
#160
0!
b10000 (
b10000000 %
b10000000 '
b1000 #
b1000 $
b1000 &
#180
1!
b10000 (
b1000000 %
b1000000 '
b1001 #
b1001 $
b1001 &
#200
0!
b10000 (
b100000 %
b100000 '
b1010 #
b1010 $
b1010 &
#220
b10000 (
b10000 %
b10000 '
b1011 #
b1011 $
b1011 &
#240
b10000 (
b1000 %
b1000 '
b1100 #
b1100 $
b1100 &
#260
b10000 (
b100 %
b100 '
b1101 #
b1101 $
b1101 &
#280
1!
b10000 (
b10 %
b10 '
b1110 #
b1110 $
b1110 &
#300
b10000 (
b1 %
b1 '
b1111 #
b1111 $
b1111 &
#320
0!
b10000 (
b0 %
b0 '
b1001 #
b1001 $
b1001 &
0"
