9/two.v
module two(En, W, F, G, H);
	input [3:0]W;
	input En;
	output F,G,H;
	wire [0:15]Y;
	decoder4t16 D(En,W,Y);
	assign F=Y[3] | Y[6] | Y[7] | Y[10] | Y[11] | Y[14];
	assign G=Y[2] | Y[3] | Y[10] | Y[14];
	assign H=Y[0] | Y[1] | Y[3] | Y[7] | Y[14] | Y[15];
endmodule

module decoder4t16(En, W, Y);
	input [3:0]W;
	input En;
	wire [0:3]E;
	output [0:15]Y;
	decoder2t4 D(En, W[3:2],E[0:3]);
	decoder2t4 D0(E[0], W[1:0],Y[0:3]);
	decoder2t4 D1(E[1], W[1:0],Y[4:7]);
	decoder2t4 D2(E[2], W[1:0],Y[8:11]);
	decoder2t4 D3(E[3], W[1:0],Y[12:15]);
endmodule

module decoder2t4(En, W, Y);
	input [1:0]W;
	input En;
	output reg [0:3]Y; 
	always @(*)
	begin
		Y=4'b0000;
		if (En==1'b0);
		else 
			case(W)
				0: Y[0]=1'b1;
				1: Y[1]=1'b1;
				2: Y[2]=1'b1;
				3: Y[3]=1'b1;
			endcase   			 
	end
endmodule

9/two_tb.v
`timescale 1ns/1ns
`include "two.v"

module two_tb();
reg [3:0]W;
reg En;
wire F,G,H;

two ex(En, W, F, G, H);
initial
begin
	$dumpfile("two_tb.vcd");
	$dumpvars(0,two_tb);
	
	En=1'b1;
	W=4'b0000; #20;
	W=4'b0001; #20;
	W=4'b0010; #20;
	W=4'b0011; #20;
	W=4'b0100; #20;
	W=4'b0101; #20;
	W=4'b0110; #20;
	W=4'b0111; #20;
	W=4'b1000; #20;
	W=4'b1001; #20;
	W=4'b1010; #20;
	W=4'b1011; #20;
	W=4'b1100; #20;
	W=4'b1101; #20;
	W=4'b1110; #20;
	W=4'b1111; #20;

	$display("test Complete");
end
endmodule

9/two_tb.vcd
$date
	Thu Oct 27 10:23:35 2022
$end
$version
	Icarus Verilog
$end
$timescale
	1ns
$end
$scope module two_tb $end
$var wire 1 ! H $end
$var wire 1 " G $end
$var wire 1 # F $end
$var reg 1 $ En $end
$var reg 4 % W [3:0] $end
$scope module ex $end
$var wire 1 $ En $end
$var wire 1 # F $end
$var wire 1 " G $end
$var wire 1 ! H $end
$var wire 4 & W [3:0] $end
$var wire 16 ' Y [0:15] $end
$scope module D $end
$var wire 1 $ En $end
$var wire 4 ( W [3:0] $end
$var wire 16 ) Y [0:15] $end
$var wire 4 * E [0:3] $end
$scope module D $end
$var wire 1 $ En $end
$var wire 2 + W [1:0] $end
$var reg 4 , Y [0:3] $end
$upscope $end
$scope module D0 $end
$var wire 1 - En $end
$var wire 2 . W [1:0] $end
$var reg 4 / Y [0:3] $end
$upscope $end
$scope module D1 $end
$var wire 1 0 En $end
$var wire 2 1 W [1:0] $end
$var reg 4 2 Y [0:3] $end
$upscope $end
$scope module D2 $end
$var wire 1 3 En $end
$var wire 2 4 W [1:0] $end
$var reg 4 5 Y [0:3] $end
$upscope $end
$scope module D3 $end
$var wire 1 6 En $end
$var wire 2 7 W [1:0] $end
$var reg 4 8 Y [0:3] $end
$upscope $end
$upscope $end
$upscope $end
$upscope $end
$enddefinitions $end
#0
$dumpvars
b0 8
b0 7
06
b0 5
b0 4
03
b0 2
b0 1
00
b1000 /
b0 .
1-
b1000 ,
b0 +
b1000 *
b1000000000000000 )
b0 (
b1000000000000000 '
b0 &
b0 %
1$
0#
0"
1!
$end
#20
b100000000000000 '
b100000000000000 )
b100 /
b1 .
b1 1
b1 4
b1 7
b1 %
b1 &
b1 (
#40
0!
1"
b10000000000000 '
b10000000000000 )
b10 /
b10 .
b10 1
b10 4
b10 7
b10 %
b10 &
b10 (
#60
1#
1!
b1000000000000 '
b1000000000000 )
b1 /
b11 .
b11 1
b11 4
b11 7
b11 %
b11 &
b11 (
#80
0#
0!
0"
b1000 2
10
0-
b100 *
b100 ,
b100000000000 '
b100000000000 )
b0 /
b1 +
b0 .
b0 1
b0 4
b0 7
b100 %
b100 &
b100 (
#100
b10000000000 '
b10000000000 )
b100 2
b1 .
b1 1
b1 4
b1 7
b101 %
b101 &
b101 (
#120
1#
b1000000000 '
b1000000000 )
b10 2
b10 .
b10 1
b10 4
b10 7
b110 %
b110 &
b110 (
#140
1!
b100000000 '
b100000000 )
b1 2
b11 .
b11 1
b11 4
b11 7
b111 %
b111 &
b111 (
#160
0#
0!
b1000 5
13
00
b10 *
b10 ,
b10000000 '
b10000000 )
b0 2
b10 +
b0 .
b0 1
b0 4
b0 7
b1000 %
b1000 &
b1000 (
#180
b1000000 '
b1000000 )
b100 5
b1 .
b1 1
b1 4
b1 7
b1001 %
b1001 &
b1001 (
#200
1#
1"
b100000 '
b100000 )
b10 5
b10 .
b10 1
b10 4
b10 7
b1010 %
b1010 &
b1010 (
#220
0"
b10000 '
b10000 )
b1 5
b11 .
b11 1
b11 4
b11 7
b1011 %
b1011 &
b1011 (
#240
0#
b1000 8
16
03
b1 *
b1 ,
b1000 '
b1000 )
b0 5
b11 +
b0 .
b0 1
b0 4
b0 7
b1100 %
b1100 &
b1100 (
#260
b100 '
b100 )
b100 8
b1 .
b1 1
b1 4
b1 7
b1101 %
b1101 &
b1101 (
#280
1!
1"
1#
b10 '
b10 )
b10 8
b10 .
b10 1
b10 4
b10 7
b1110 %
b1110 &
b1110 (
#300
0"
0#
b1 '
b1 )
b1 8
b11 .
b11 1
b11 4
b11 7
b1111 %
b1111 &
b1111 (
