11/three.v
module three(clk, reset, out);
	input clk,reset;
	output [3:0]out;
	TFF d0(1'b1,clk,reset,out[0]);
	TFF d1(1'b1,out[0],reset,out[1]);
	TFF d2(1'b1,out[1],reset,out[2]);
	TFF d3(1'b1,out[2],reset,out[3]);
endmodule

module TFF(t,clk,reset,q);
	input t,clk,reset;
	output reg q;
	always@(negedge clk)
	begin
		if(!reset)
			q<=0;
		else
		begin  
			if(t)
				q<=~q;
			else
				q<=q;
		end
	end
endmodule

11/three_tb.v
`timescale 1ns/1ns
`include "three.v" 
module three_tb();
reg clk, reset; 
wire [3:0]out;
three ex(clk, reset, out);
initial
begin
	$dumpfile("three_tb.vcd");
	$dumpvars(0, three_tb);
	clk=0; 
	forever #20 clk = ~clk;
end
initial
begin
	reset=0;#40;
	reset=1;
	$display("Test complete");
end
endmodule

11/three_tb.vcd
$date
	Thu Nov 17 11:09:54 2022
$end
$version
	Icarus Verilog
$end
$timescale
	1ns
$end
$scope module three_tb $end
$var wire 4 ! out [3:0] $end
$var reg 1 " clk $end
$var reg 1 # reset $end
$scope module ex $end
$var wire 1 " clk $end
$var wire 1 # reset $end
$var wire 4 $ out [3:0] $end
$scope module d0 $end
$var wire 1 " clk $end
$var wire 1 # reset $end
$var wire 1 % t $end
$var reg 1 & q $end
$upscope $end
$scope module d1 $end
$var wire 1 ' clk $end
$var wire 1 # reset $end
$var wire 1 ( t $end
$var reg 1 ) q $end
$upscope $end
$scope module d2 $end
$var wire 1 * clk $end
$var wire 1 # reset $end
$var wire 1 + t $end
$var reg 1 , q $end
$upscope $end
$scope module d3 $end
$var wire 1 - clk $end
$var wire 1 # reset $end
$var wire 1 . t $end
$var reg 1 / q $end
$upscope $end
$upscope $end
$upscope $end
$enddefinitions $end
#0
$dumpvars
0/
1.
0-
0,
1+
0*
0)
1(
0'
0&
1%
b0 $
0#
0"
b0 !
$end
#20
1"
#40
1'
b1 !
b1 $
1&
0"
1#
#60
1"
#80
1*
1)
0'
b10 !
b10 $
0&
0"
#100
1"
#120
1'
b11 !
b11 $
1&
0"
#140
1"
#160
1-
1,
0*
0)
0'
b100 !
b100 $
0&
0"
#180
1"
#200
1'
b101 !
b101 $
1&
0"
#220
1"
#240
1*
1)
0'
b110 !
b110 $
0&
0"
#260
1"
#280
1'
b111 !
b111 $
1&
0"
#300
1"
#320
1/
0-
0,
0*
0)
0'
b1000 !
b1000 $
0&
0"
#340
1"
#360
1'
b1001 !
b1001 $
1&
0"
#380
1"
#400
1*
1)
0'
b1010 !
b1010 $
0&
0"
#420
1"
#440
1'
b1011 !
b1011 $
1&
0"
#460
1"
#480
1-
1,
0*
0)
0'
b1100 !
b1100 $
0&
0"
#500
1"
#520
1'
b1101 !
b1101 $
1&
0"
#540
1"
#560
1*
1)
0'
b1110 !
b1110 $
0&
0"
#580
1"
#600
1'
b1111 !
b1111 $
1&
0"
#620
1"
#640
0/
0-
0,
0*
0)
0'
b0 !
b0 $
0&
0"
#660
1"
#680
1'
b1 !
b1 $
1&
0"
#700
1"
#720
1*
1)
0'
b10 !
b10 $
0&
0"
#740
1"
#760
1'
b11 !
b11 $
1&
0"
#780
1"
#800
1-
1,
0*
0)
0'
b100 !
b100 $
0&
0"
#820
1"
#840
1'
b101 !
b101 $
1&
0"
#860
1"
#880
1*
1)
0'
b110 !
b110 $
0&
0"
#900
1"
#920
1'
b111 !
b111 $
1&
0"
#940
1"
#960
1/
0-
0,
0*
0)
0'
b1000 !
b1000 $
0&
0"
#980
1"
#1000
1'
b1001 !
b1001 $
1&
0"
#1020
1"
#1040
1*
1)
0'
b1010 !
b1010 $
0&
0"
#1060
1"
#1080
1'
b1011 !
b1011 $
1&
0"
#1100
1"
#1120
1-
1,
0*
0)
0'
b1100 !
b1100 $
0&
0"
#1140
1"
#1160
1'
b1101 !
b1101 $
1&
0"
#1180
1"
#1200
1*
1)
0'
b1110 !
b1110 $
0&
0"
#1220
1"
#1240
1'
b1111 !
b1111 $
1&
0"
#1260
1"
#1280
0/
0-
0,
0*
0)
0'
b0 !
b0 $
0&
0"
#1300
1"
#1320
1'
b1 !
b1 $
1&
0"
#1340
1"
#1360
1*
1)
0'
b10 !
b10 $
0&
0"
#1380
1"
#1400
1'
b11 !
b11 $
1&
0"
#1420
1"
#1440
1-
1,
0*
0)
0'
b100 !
b100 $
0&
0"
#1460
1"
#1480
1'
b101 !
b101 $
1&
0"
#1500
1"
#1520
1*
1)
0'
b110 !
b110 $
0&
0"
#1540
1"
#1560
1'
b111 !
b111 $
1&
0"
#1580
1"
#1600
1/
0-
0,
0*
0)
0'
b1000 !
b1000 $
0&
0"
#1620
1"
#1640
1'
b1001 !
b1001 $
1&
0"
#1660
1"
#1680
1*
1)
0'
b1010 !
b1010 $
0&
0"
#1700
1"
#1720
1'
b1011 !
b1011 $
1&
0"
#1740
1"
#1760
1-
1,
0*
0)
0'
b1100 !
b1100 $
0&
0"
#1780
1"
#1800
1'
b1101 !
b1101 $
1&
0"
#1820
1"
#1840
1*
1)
0'
b1110 !
b1110 $
0&
0"
#1860
1"
#1880
1'
b1111 !
b1111 $
1&
0"
#1900
1"
#1920
0/
0-
0,
0*
0)
0'
b0 !
b0 $
0&
0"
#1940
1"
#1960
1'
b1 !
b1 $
1&
0"
#1980
1"
#2000
1*
1)
0'
b10 !
b10 $
0&
0"
#2020
1"
#2040
1'
b11 !
b11 $
1&
0"
#2060
1"
#2080
1-
1,
0*
0)
0'
b100 !
b100 $
0&
0"
#2100
1"
#2120
1'
b101 !
b101 $
1&
0"
#2140
1"
#2160
1*
1)
0'
b110 !
b110 $
0&
0"
#2180
1"
#2200
1'
b111 !
b111 $
1&
0"
#2220
1"
#2240
1/
0-
0,
0*
0)
0'
b1000 !
b1000 $
0&
0"
#2260
1"
#2280
1'
b1001 !
b1001 $
1&
0"
#2300
1"
#2320
1*
1)
0'
b1010 !
b1010 $
0&
0"
#2340
1"
#2360
1'
b1011 !
b1011 $
1&
0"
#2380
1"
#2400
1-
1,
0*
0)
0'
b1100 !
b1100 $
0&
0"
#2420
1"
#2440
1'
b1101 !
b1101 $
1&
0"
#2460
1"
#2480
1*
1)
0'
b1110 !
b1110 $
0&
0"
#2500
1"
#2520
1'
b1111 !
b1111 $
1&
0"
#2540
1"
#2560
0/
0-
0,
0*
0)
0'
b0 !
b0 $
0&
0"
#2580
1"
#2600
1'
b1 !
b1 $
1&
0"
#2620
1"
#2640
1*
1)
0'
b10 !
b10 $
0&
0"
#2660
1"
#2680
1'
b11 !
b11 $
1&
0"
#2700
1"
#2720
1-
1,
0*
0)
0'
b100 !
b100 $
0&
0"
#2740
1"
#2760
1'
b101 !
b101 $
1&
0"
#2780
1"
#2800
1*
1)
0'
b110 !
b110 $
0&
0"
#2820
1"
#2840
1'
b111 !
b111 $
1&
0"
#2860
1"
#2880
1/
0-
0,
0*
0)
0'
b1000 !
b1000 $
0&
0"
#2900
1"
#2920
1'
b1001 !
b1001 $
1&
0"
#2940
1"
#2960
1*
1)
0'
b1010 !
b1010 $
0&
0"
#2980
1"
#3000
1'
b1011 !
b1011 $
1&
0"
#3020
1"
#3040
1-
1,
0*
0)
0'
b1100 !
b1100 $
0&
0"
#3060
1"
#3080
1'
b1101 !
b1101 $
1&
0"
#3100
1"
#3120
1*
1)
0'
b1110 !
b1110 $
0&
0"
#3140
1"
#3160
1'
b1111 !
b1111 $
1&
0"
#3180
1"
#3200
0/
0-
0,
0*
0)
0'
b0 !
b0 $
0&
0"
#3220
1"
#3240
1'
b1 !
b1 $
1&
0"
#3260
1"
#3280
1*
1)
0'
b10 !
b10 $
0&
0"
#3300
1"
#3320
1'
b11 !
b11 $
1&
0"
#3340
1"
#3360
1-
1,
0*
0)
0'
b100 !
b100 $
0&
0"
#3380
1"
#3400
1'
b101 !
b101 $
1&
0"
#3420
1"
#3440
1*
1)
0'
b110 !
b110 $
0&
0"
#3460
1"
#3480
1'
b111 !
b111 $
1&
0"
#3500
1"
#3520
1/
0-
0,
0*
0)
0'
b1000 !
b1000 $
0&
0"
#3540
1"
#3560
1'
b1001 !
b1001 $
1&
0"
#3580
1"
#3600
1*
1)
0'
b1010 !
b1010 $
0&
0"
#3620
1"
#3640
1'
b1011 !
b1011 $
1&
0"
#3660
1"
#3680
1-
1,
0*
0)
0'
b1100 !
b1100 $
0&
0"
#3700
1"
#3720
1'
b1101 !
b1101 $
1&
0"
#3740
1"
#3760
1*
1)
0'
b1110 !
b1110 $
0&
0"
#3780
1"
#3800
1'
b1111 !
b1111 $
1&
0"
#3820
1"
#3840
0/
0-
0,
0*
0)
0'
b0 !
b0 $
0&
0"
#3860
1"
#3880
1'
b1 !
b1 $
1&
0"
#3900
1"
#3920
1*
1)
0'
b10 !
b10 $
0&
0"
#3940
1"
#3960
1'
b11 !
b11 $
1&
0"
#3980
1"
#4000
1-
1,
0*
0)
0'
b100 !
b100 $
0&
0"
#4020
1"
#4040
1'
b101 !
b101 $
1&
0"
#4060
1"
#4080
1*
1)
0'
b110 !
b110 $
0&
0"
#4100
1"
#4120
1'
b111 !
b111 $
1&
0"
#4140
1"
#4160
1/
0-
0,
0*
0)
0'
b1000 !
b1000 $
0&
0"
#4180
1"
#4200
1'
b1001 !
b1001 $
1&
0"
#4220
1"
#4240
1*
1)
0'
b1010 !
b1010 $
0&
0"
#4260
1"
#4280
1'
b1011 !
b1011 $
1&
0"
#4300
1"
#4320
1-
1,
0*
0)
0'
b1100 !
b1100 $
0&
0"
#4340
1"
#4360
1'
b1101 !
b1101 $
1&
0"
#4380
1"
#4400
1*
1)
0'
b1110 !
b1110 $
0&
0"
#4420
1"
#4440
1'
b1111 !
b1111 $
1&
0"
#4460
1"
#4480
0/
0-
0,
0*
0)
0'
b0 !
b0 $
0&
0"
#4500
1"
#4520
1'
b1 !
b1 $
1&
0"
#4540
1"
#4560
1*
1)
0'
b10 !
b10 $
0&
0"
#4580
1"
#4600
1'
b11 !
b11 $
1&
0"
#4620
1"
#4640
1-
1,
0*
0)
0'
b100 !
b100 $
0&
0"
#4660
1"
#4680
1'
b101 !
b101 $
1&
0"
#4700
1"
#4720
1*
1)
0'
b110 !
b110 $
0&
0"
#4740
1"
#4760
1'
b111 !
b111 $
1&
0"
#4780
1"
#4800
1/
0-
0,
0*
0)
0'
b1000 !
b1000 $
0&
0"
#4820
1"
#4840
1'
b1001 !
b1001 $
1&
0"
#4860
1"
#4880
1*
1)
0'
b1010 !
b1010 $
0&
0"
#4900
1"
#4920
1'
b1011 !
b1011 $
1&
0"
#4940
1"
#4960
1-
1,
0*
0)
0'
b1100 !
b1100 $
0&
0"
#4980
1"
#5000
1'
b1101 !
b1101 $
1&
0"
#5020
1"
#5040
1*
1)
0'
b1110 !
b1110 $
0&
0"
#5060
1"
#5080
1'
b1111 !
b1111 $
1&
0"
#5100
1"
#5120
0/
0-
0,
0*
0)
0'
b0 !
b0 $
0&
0"
#5140
1"
#5160
1'
b1 !
b1 $
1&
0"
#5180
1"
#5200
1*
1)
0'
b10 !
b10 $
0&
0"
#5220
1"
#5240
1'
b11 !
b11 $
1&
0"
#5260
1"
#5280
1-
1,
0*
0)
0'
b100 !
b100 $
0&
0"
#5300
1"
#5320
1'
b101 !
b101 $
1&
0"
#5340
1"
#5360
1*
1)
0'
b110 !
b110 $
0&
0"
#5380
1"
#5400
1'
b111 !
b111 $
1&
0"
#5420
1"
#5440
1/
0-
0,
0*
0)
0'
b1000 !
b1000 $
0&
0"
#5460
1"
#5480
1'
b1001 !
b1001 $
1&
0"
#5500
1"
#5520
1*
1)
0'
b1010 !
b1010 $
0&
0"
#5540
1"
#5560
1'
b1011 !
b1011 $
1&
0"
#5580
1"
#5600
1-
1,
0*
0)
0'
b1100 !
b1100 $
0&
0"
#5620
1"
#5640
1'
b1101 !
b1101 $
1&
0"
#5660
1"
#5680
1*
1)
0'
b1110 !
b1110 $
0&
0"
#5700
1"
#5720
1'
b1111 !
b1111 $
1&
0"
#5740
1"
#5760
0/
0-
0,
0*
0)
0'
b0 !
b0 $
0&
0"
#5780
1"
#5800
1'
b1 !
b1 $
1&
0"
#5820
1"
#5840
1*
1)
0'
b10 !
b10 $
0&
0"
#5860
1"
#5880
1'
b11 !
b11 $
1&
0"
#5900
1"
#5920
1-
1,
0*
0)
0'
b100 !
b100 $
0&
0"
#5940
1"
#5960
1'
b101 !
b101 $
1&
0"
#5980
1"
#6000
1*
1)
0'
b110 !
b110 $
0&
0"
#6020
1"
#6040
1'
b111 !
b111 $
1&
0"
#6060
1"
#6080
1/
0-
0,
0*
0)
0'
b1000 !
b1000 $
0&
0"
#6100
1"
#6120
1'
b1001 !
b1001 $
1&
0"
#6140
1"
#6160
1*
1)
0'
b1010 !
b1010 $
0&
0"
#6180
1"
#6200
1'
b1011 !
b1011 $
1&
0"
#6220
1"
#6240
1-
1,
0*
0)
0'
b1100 !
b1100 $
0&
0"
#6260
1"
#6280
1'
b1101 !
b1101 $
1&
0"
#6300
1"
#6320
1*
1)
0'
b1110 !
b1110 $
0&
0"
#6340
1"
#6360
1'
b1111 !
b1111 $
1&
0"
#6380
1"
#6400
0/
0-
0,
0*
0)
0'
b0 !
b0 $
0&
0"
#6420
1"
#6440
1'
b1 !
b1 $
1&
0"
#6460
1"
#6480
1*
1)
0'
b10 !
b10 $
0&
0"
#6500
1"
#6520
1'
b11 !
b11 $
1&
0"
#6540
1"
#6560
1-
1,
0*
0)
0'
b100 !
b100 $
0&
0"
#6580
1"
#6600
1'
b101 !
b101 $
1&
0"
#6620
1"
#6640
1*
1)
0'
b110 !
b110 $
0&
0"
#6660
1"
#6680
1'
b111 !
b111 $
1&
0"
#6700
1"
#6720
1/
0-
0,
0*
0)
0'
b1000 !
b1000 $
0&
0"
#6740
1"
#6760
1'
b1001 !
b1001 $
1&
0"
#6780
1"
#6800
1*
1)
0'
b1010 !
b1010 $
0&
0"
#6820
1"
#6840
1'
b1011 !
b1011 $
1&
0"
#6860
1"
#6880
1-
1,
0*
0)
0'
b1100 !
b1100 $
0&
0"
#6900
1"
#6920
1'
b1101 !
b1101 $
1&
0"
#6940
1"
#6960
1*
1)
0'
b1110 !
b1110 $
0&
0"
#6980
1"
#7000
1'
b1111 !
b1111 $
1&
0"
#7020
1"
#7040
0/
0-
0,
0*
0)
0'
b0 !
b0 $
0&
0"
#7060
1"
#7080
1'
b1 !
b1 $
1&
0"
#7100
1"
#7120
1*
1)
0'
b10 !
b10 $
0&
0"
#7140
1"
#7160
1'
b11 !
b11 $
1&
0"
#7180
1"
#7200
1-
1,
0*
0)
0'
b100 !
b100 $
0&
0"
#7220
1"
#7240
1'
b101 !
b101 $
1&
0"
#7260
1"
#7280
1*
1)
0'
b110 !
b110 $
0&
0"
#7300
1"
#7320
1'
b111 !
b111 $
1&
0"
#7340
1"
#7360
1/
0-
0,
0*
0)
0'
b1000 !
b1000 $
0&
0"
#7380
1"
#7400
1'
b1001 !
b1001 $
1&
0"
#7420
1"
#7440
1*
1)
0'
b1010 !
b1010 $
0&
0"
#7460
1"
#7480
1'
b1011 !
b1011 $
1&
0"
#7500
1"
#7520
1-
1,
0*
0)
0'
b1100 !
b1100 $
0&
0"
#7540
1"
#7560
1'
b1101 !
b1101 $
1&
0"
#7580
1"
#7600
1*
1)
0'
b1110 !
b1110 $
0&
0"
#7620
1"
#7640
1'
b1111 !
b1111 $
1&
0"
#7660
1"
#7680
0/
0-
0,
0*
0)
0'
b0 !
b0 $
0&
0"
#7700
1"
#7720
1'
b1 !
b1 $
1&
0"
#7740
1"
#7760
1*
1)
0'
b10 !
b10 $
0&
0"
#7780
1"
#7800
1'
b11 !
b11 $
1&
0"
#7820
1"
#7840
1-
1,
0*
0)
0'
b100 !
b100 $
0&
0"
#7860
1"
#7880
1'
b101 !
b101 $
1&
0"
#7900
1"
#7920
1*
1)
0'
b110 !
b110 $
0&
0"
#7940
1"
#7960
1'
b111 !
b111 $
1&
0"
#7980
1"
#8000
1/
0-
0,
0*
0)
0'
b1000 !
b1000 $
0&
0"
#8020
1"
#8040
1'
b1001 !
b1001 $
1&
0"
#8060
1"
#8080
1*
1)
0'
b1010 !
b1010 $
0&
0"
#8100
1"
#8120
1'
b1011 !
b1011 $
1&
0"
#8140
1"
#8160
1-
1,
0*
0)
0'
b1100 !
b1100 $
0&
0"
#8180
1"
#8200
1'
b1101 !
b1101 $
1&
0"
#8220
1"
#8240
1*
1)
0'
b1110 !
b1110 $
0&
0"
#8260
1"
#8280
1'
b1111 !
b1111 $
1&
0"
#8300
1"
#8320
0/
0-
0,
0*
0)
0'
b0 !
b0 $
0&
0"
#8340
1"
#8360
1'
b1 !
b1 $
1&
0"
#8380
1"
#8400
1*
1)
0'
b10 !
b10 $
0&
0"
#8420
1"
#8440
1'
b11 !
b11 $
1&
0"
#8460
1"
#8480
1-
1,
0*
0)
0'
b100 !
b100 $
0&
0"
#8500
1"
#8520
1'
b101 !
b101 $
1&
0"
#8540
1"
#8560
1*
1)
0'
b110 !
b110 $
0&
0"
#8580
1"
#8600
1'
b111 !
b111 $
1&
0"
#8620
1"
#8640
1/
0-
0,
0*
0)
0'
b1000 !
b1000 $
0&
0"
#8660
1"
#8680
1'
b1001 !
b1001 $
1&
0"
#8700
1"
#8720
1*
1)
0'
b1010 !
b1010 $
0&
0"
#8740
1"
#8760
1'
b1011 !
b1011 $
1&
0"
#8780
1"
#8800
1-
1,
0*
0)
0'
b1100 !
b1100 $
0&
0"
#8820
1"
#8840
1'
b1101 !
b1101 $
1&
0"
#8860
1"
#8880
1*
1)
0'
b1110 !
b1110 $
0&
0"
#8900
1"
#8920
1'
b1111 !
b1111 $
1&
0"
#8940
1"
#8960
0/
0-
0,
0*
0)
0'
b0 !
b0 $
0&
0"
#8980
1"
#9000
1'
b1 !
b1 $
1&
0"
#9020
1"
#9040
1*
1)
0'
b10 !
b10 $
0&
0"
#9060
1"
#9080
1'
b11 !
b11 $
1&
0"
#9100
1"
#9120
1-
1,
0*
0)
0'
b100 !
b100 $
0&
0"
#9140
1"
#9160
1'
b101 !
b101 $
1&
0"
#9180
1"
#9200
1*
1)
0'
b110 !
b110 $
0&
0"
#9220
1"
#9240
1'
b111 !
b111 $
1&
0"
#9260
1"
#9280
1/
0-
0,
0*
0)
0'
b1000 !
b1000 $
0&
0"
#9300
1"
#9320
1'
b1001 !
b1001 $
1&
0"
#9340
1"
#9360
1*
1)
0'
b1010 !
b1010 $
0&
0"
#9380
1"
#9400
1'
b1011 !
b1011 $
1&
0"
#9420
1"
#9440
1-
1,
0*
0)
0'
b1100 !
b1100 $
0&
0"
#9460
1"
#9480
1'
b1101 !
b1101 $
1&
0"
#9500
1"
#9520
1*
1)
0'
b1110 !
b1110 $
0&
0"
#9540
1"
#9560
1'
b1111 !
b1111 $
1&
0"
#9580
1"
#9600
0/
0-
0,
0*
0)
0'
b0 !
b0 $
0&
0"
#9620
1"
#9640
1'
b1 !
b1 $
1&
0"
#9660
1"
#9680
1*
1)
0'
b10 !
b10 $
0&
0"
#9700
1"
#9720
1'
b11 !
b11 $
1&
0"
#9740
1"
#9760
1-
1,
0*
0)
0'
b100 !
b100 $
0&
0"
#9780
1"
#9800
1'
b101 !
b101 $
1&
0"
#9820
1"
#9840
1*
1)
0'
b110 !
b110 $
0&
0"
#9860
1"
#9880
1'
b111 !
b111 $
1&
0"
#9900
1"
#9920
1/
0-
0,
0*
0)
0'
b1000 !
b1000 $
0&
0"
#9940
1"
#9960
1'
b1001 !
b1001 $
1&
0"
#9980
1"
#10000
1*
1)
0'
b1010 !
b1010 $
0&
0"
#10020
1"
#10040
1'
b1011 !
b1011 $
1&
0"
#10060
1"
#10080
1-
1,
0*
0)
0'
b1100 !
b1100 $
0&
0"
#10100
1"
#10120
1'
b1101 !
b1101 $
1&
0"
#10140
1"
#10160
1*
1)
0'
b1110 !
b1110 $
0&
0"
#10180
1"
#10200
1'
b1111 !
b1111 $
1&
0"
#10220
1"
#10240
0/
0-
0,
0*
0)
0'
b0 !
b0 $
0&
0"
#10260
1"
#10280
1'
b1 !
b1 $
1&
0"
#10300
1"
#10320
1*
1)
0'
b10 !
b10 $
0&
0"
#10340
1"
#10360
1'
b11 !
b11 $
1&
0"
#10380
1"
#10400
1-
1,
0*
0)
0'
b100 !
b100 $
0&
0"
#10420
1"
#10440
1'
b101 !
b101 $
1&
0"
#10460
1"
#10480
1*
1)
0'
b110 !
b110 $
0&
0"
#10500
1"
#10520
1'
b111 !
b111 $
1&
0"
#10540
1"
#10560
1/
0-
0,
0*
0)
0'
b1000 !
b1000 $
0&
0"
#10580
1"
#10600
1'
b1001 !
b1001 $
1&
0"
#10620
1"
#10640
1*
1)
0'
b1010 !
b1010 $
0&
0"
#10660
1"
#10680
1'
b1011 !
b1011 $
1&
0"
#10700
1"
#10720
1-
1,
0*
0)
0'
b1100 !
b1100 $
0&
0"
#10740
1"
#10760
1'
b1101 !
b1101 $
1&
0"
#10780
1"
#10800
1*
1)
0'
b1110 !
b1110 $
0&
0"
#10820
1"
#10840
1'
b1111 !
b1111 $
1&
0"
#10860
1"
#10880
0/
0-
0,
0*
0)
0'
b0 !
b0 $
0&
0"
#10900
1"
#10920
1'
b1 !
b1 $
1&
0"
#10940
1"
#10960
1*
1)
0'
b10 !
b10 $
0&
0"
#10980
1"
#11000
1'
b11 !
b11 $
1&
0"
#11020
1"
#11040
1-
1,
0*
0)
0'
b100 !
b100 $
0&
0"
#11060
1"
#11080
1'
b101 !
b101 $
1&
0"
#11100
1"
#11120
1*
1)
0'
b110 !
b110 $
0&
0"
#11140
1"
#11160
1'
b111 !
b111 $
1&
0"
#11180
1"
#11200
1/
0-
0,
0*
0)
0'
b1000 !
b1000 $
0&
0"
#11220
1"
#11240
1'
b1001 !
b1001 $
1&
0"
#11260
1"
#11280
1*
1)
0'
b1010 !
b1010 $
0&
0"
#11300
1"
#11320
1'
b1011 !
b1011 $
1&
0"
#11340
1"
#11360
1-
1,
0*
0)
0'
b1100 !
b1100 $
0&
0"
#11380
1"
#11400
1'
b1101 !
b1101 $
1&
0"
#11420
1"
#11440
1*
1)
0'
b1110 !
b1110 $
0&
0"
#11460
1"
#11480
1'
b1111 !
b1111 $
1&
0"
#11500
1"
#11520
0/
0-
0,
0*
0)
0'
b0 !
b0 $
0&
0"
#11540
1"
#11560
1'
b1 !
b1 $
1&
0"
#11580
1"
#11600
1*
1)
0'
b10 !
b10 $
0&
0"
#11620
1"
#11640
1'
b11 !
b11 $
1&
0"
#11660
1"
#11680
1-
1,
0*
0)
0'
b100 !
b100 $
0&
0"
#11700
1"
#11720
1'
b101 !
b101 $
1&
0"
#11740
1"
#11760
1*
1)
0'
b110 !
b110 $
0&
0"
#11780
1"
#11800
1'
b111 !
b111 $
1&
0"
#11820
1"
#11840
1/
0-
0,
0*
0)
0'
b1000 !
b1000 $
0&
0"
#11860
1"
#11880
1'
b1001 !
b1001 $
1&
0"
#11900
1"
#11920
1*
1)
0'
b1010 !
b1010 $
0&
0"
#11940
1"
#11960
1'
b1011 !
b1011 $
1&
0"
#11980
1"
#12000
1-
1,
0*
0)
0'
b1100 !
b1100 $
0&
0"
#12020
1"
#12040
1'
b1101 !
b1101 $
1&
0"
#12060
1"
#12080
1*
1)
0'
b1110 !
b1110 $
0&
0"
#12100
1"
#12120
1'
b1111 !
b1111 $
1&
0"
#12140
1"
#12160
0/
0-
0,
0*
0)
0'
b0 !
b0 $
0&
0"
#12180
1"
#12200
1'
b1 !
b1 $
1&
0"
#12220
1"
#12240
1*
1)
0'
b10 !
b10 $
0&
0"
#12260
1"
#12280
1'
b11 !
b11 $
1&
0"
#12300
1"
#12320
1-
1,
0*
0)
0'
b100 !
b100 $
0&
0"
#12340
1"
#12360
1'
b101 !
b101 $
1&
0"
#12380
1"
#12400
1*
1)
0'
b110 !
b110 $
0&
0"
#12420
1"
#12440
1'
b111 !
b111 $
1&
0"
#12460
1"
#12480
1/
0-
0,
0*
0)
0'
b1000 !
b1000 $
0&
0"
#12500
1"
#12520
1'
b1001 !
b1001 $
1&
0"
#12540
1"
#12560
1*
1)
0'
b1010 !
b1010 $
0&
0"
#12580
1"
#12600
1'
b1011 !
b1011 $
1&
0"
#12620
1"
#12640
1-
1,
0*
0)
0'
b1100 !
b1100 $
0&
0"
#12660
1"
#12680
1'
b1101 !
b1101 $
1&
0"
#12700
1"
#12720
1*
1)
0'
b1110 !
b1110 $
0&
0"
#12740
1"
#12760
1'
b1111 !
b1111 $
1&
0"
#12780
1"
#12800
0/
0-
0,
0*
0)
0'
b0 !
b0 $
0&
0"
#12820
1"
#12840
1'
b1 !
b1 $
1&
0"
#12860
1"
#12880
1*
1)
0'
b10 !
b10 $
0&
0"
#12900
1"
#12920
1'
b11 !
b11 $
1&
0"
#12940
1"
#12960
1-
1,
0*
0)
0'
b100 !
b100 $
0&
0"
#12980
1"
#13000
1'
b101 !
b101 $
1&
0"
#13020
1"
#13040
1*
1)
0'
b110 !
b110 $
0&
0"
#13060
1"
#13080
1'
b111 !
b111 $
1&
0"
#13100
1"
#13120
1/
0-
0,
0*
0)
0'
b1000 !
b1000 $
0&
0"
#13140
1"
#13160
1'
b1001 !
b1001 $
1&
0"
#13180
1"
#13200
1*
1)
0'
b1010 !
b1010 $
0&
0"
#13220
1"
#13240
1'
b1011 !
b1011 $
1&
0"
#13260
1"
#13280
1-
1,
0*
0)
0'
b1100 !
b1100 $
0&
0"
#13300
1"
#13320
1'
b1101 !
b1101 $
1&
0"
#13340
1"
#13360
1*
1)
0'
b1110 !
b1110 $
0&
0"
#13380
1"
#13400
1'
b1111 !
b1111 $
1&
0"
#13420
1"
#13440
0/
0-
0,
0*
0)
0'
b0 !
b0 $
0&
0"
#13460
1"
#13480
1'
b1 !
b1 $
1&
0"
#13500
1"
#13520
1*
1)
0'
b10 !
b10 $
0&
0"
#13540
1"
#13560
1'
b11 !
b11 $
1&
0"
#13580
1"
#13600
1-
1,
0*
0)
0'
b100 !
b100 $
0&
0"
#13620
1"
#13640
1'
b101 !
b101 $
1&
0"
#13660
1"
#13680
1*
1)
0'
b110 !
b110 $
0&
0"
#13700
1"
#13720
1'
b111 !
b111 $
1&
0"
#13740
1"
#13760
1/
0-
0,
0*
0)
0'
b1000 !
b1000 $
0&
0"
#13780
1"
#13800
1'
b1001 !
b1001 $
1&
0"
#13820
1"
#13840
1*
1)
0'
b1010 !
b1010 $
0&
0"
#13860
1"
#13880
1'
b1011 !
b1011 $
1&
0"
#13900
1"
#13920
1-
1,
0*
0)
0'
b1100 !
b1100 $
0&
0"
#13940
1"
#13960
1'
b1101 !
b1101 $
1&
0"
#13980
1"
#14000
1*
1)
0'
b1110 !
b1110 $
0&
0"
#14020
1"
#14040
1'
b1111 !
b1111 $
1&
0"
#14060
1"
#14080
0/
0-
0,
0*
0)
0'
b0 !
b0 $
0&
0"
#14100
1"
#14120
1'
b1 !
b1 $
1&
0"
#14140
1"
#14160
1*
1)
0'
b10 !
b10 $
0&
0"
#14180
1"
#14200
1'
b11 !
b11 $
1&
0"
#14220
1"
#14240
1-
1,
0*
0)
0'
b100 !
b100 $
0&
0"
#14260
1"
#14280
1'
b101 !
b101 $
1&
0"
#14300
1"
#14320
1*
1)
0'
b110 !
b110 $
0&
0"
#14340
1"
#14360
1'
b111 !
b111 $
1&
0"
#14380
1"
#14400
1/
0-
0,
0*
0)
0'
b1000 !
b1000 $
0&
0"
#14420
1"
#14440
1'
b1001 !
b1001 $
1&
0"
#14460
1"
#14480
1*
1)
0'
b1010 !
b1010 $
0&
0"
#14500
1"
#14520
1'
b1011 !
b1011 $
1&
0"
#14540
1"
#14560
1-
1,
0*
0)
0'
b1100 !
b1100 $
0&
0"
#14580
1"
#14600
1'
b1101 !
b1101 $
1&
0"
#14620
1"
#14640
1*
1)
0'
b1110 !
b1110 $
0&
0"
#14660
1"
#14680
1'
b1111 !
b1111 $
1&
0"
#14700
1"
#14720
0/
0-
0,
0*
0)
0'
b0 !
b0 $
0&
0"
#14740
1"
#14760
1'
b1 !
b1 $
1&
0"
#14780
1"
#14800
1*
1)
0'
b10 !
b10 $
0&
0"
#14820
1"
#14840
1'
b11 !
b11 $
1&
0"
#14860
1"
#14880
1-
1,
0*
0)
0'
b100 !
b100 $
0&
0"
#14900
1"
#14920
1'
b101 !
b101 $
1&
0"
#14940
1"
#14960
1*
1)
0'
b110 !
b110 $
0&
0"
#14980
1"
#15000
1'
b111 !
b111 $
1&
0"
#15020
1"
#15040
1/
0-
0,
0*
0)
0'
b1000 !
b1000 $
0&
0"
#15060
1"
#15080
1'
b1001 !
b1001 $
1&
0"
#15100
1"
#15120
1*
1)
0'
b1010 !
b1010 $
0&
0"
#15140
1"
#15160
1'
b1011 !
b1011 $
1&
0"
#15180
1"
#15200
1-
1,
0*
0)
0'
b1100 !
b1100 $
0&
0"
#15220
1"
#15240
1'
b1101 !
b1101 $
1&
0"
#15260
1"
#15280
1*
1)
0'
b1110 !
b1110 $
0&
0"
#15300
1"
#15320
1'
b1111 !
b1111 $
1&
0"
#15340
1"
#15360
0/
0-
0,
0*
0)
0'
b0 !
b0 $
0&
0"
#15380
1"
#15400
1'
b1 !
b1 $
1&
0"
#15420
1"
#15440
1*
1)
0'
b10 !
b10 $
0&
0"
#15460
1"
#15480
1'
b11 !
b11 $
1&
0"
#15500
1"
#15520
1-
1,
0*
0)
0'
b100 !
b100 $
0&
0"
#15540
1"
#15560
1'
b101 !
b101 $
1&
0"
#15580
1"
#15600
1*
1)
0'
b110 !
b110 $
0&
0"
#15620
1"
#15640
1'
b111 !
b111 $
1&
0"
#15660
1"
#15680
1/
0-
0,
0*
0)
0'
b1000 !
b1000 $
0&
0"
#15700
1"
#15720
1'
b1001 !
b1001 $
1&
0"
