7/two_a.v
module two_a(W, f);
	input [0:2]W;
	output f;
	and(m0,	W[1], W[2]);
	or(m1, W[1], W[2]);
	mux2to1 M2(m0, m1, W[0], f);
endmodule

module mux2to1(w0, w1, s, f);
	input w0, w1, s;
	output reg f;
	
	always @(w0 or w1 or s)
	begin
		f=s==1?w1:w0;
	end
endmodule

7/two_a_tb.v
`timescale 1ns/1ns
`include "two_a.v"
 
module two_a_tb();
reg [0:2]W;
wire f;

two_a ex(W, f); 
initial
begin
	$dumpfile("two_a_tb.vcd");
	$dumpvars(0, two_a_tb);
	W=3'b000; #20;
	W=3'b001; #20;
	W=3'b010; #20;
	W=3'b011; #20;
	W=3'b100; #20;
	W=3'b101; #20;
	W=3'b110; #20;
	W=3'b111; #20;
	$display("Test complete");
end
endmodule

7/two_a_tb.vcd
$date
	Thu Oct 13 11:05:36 2022
$end
$version
	Icarus Verilog
$end
$timescale
	1ns
$end
$scope module two_a_tb $end
$var wire 1 ! f $end
$var reg 3 " W [0:2] $end
$scope module ex $end
$var wire 3 # W [0:2] $end
$var wire 1 $ m0 $end
$var wire 1 % m1 $end
$var wire 1 ! f $end
$scope module M2 $end
$var wire 1 & s $end
$var wire 1 $ w0 $end
$var wire 1 % w1 $end
$var reg 1 ! f $end
$upscope $end
$upscope $end
$upscope $end
$enddefinitions $end
#0
$dumpvars
0&
0%
0$
b0 #
b0 "
0!
$end
#20
1%
b1 "
b1 #
#40
b10 "
b10 #
#60
1!
1$
b11 "
b11 #
#80
0!
0$
0%
1&
b100 "
b100 #
#100
1!
1%
b101 "
b101 #
#120
b110 "
b110 #
#140
1$
b111 "
b111 #
