3/three.v
module three(A,B,C,D,f);
	input A,B,C,D;
	output f;
	
	nor(a,A,A);
	nor(c,C,C);
	nor(d,D,D);
	nor(l,a,c);
	nor(f,l,d);
		
endmodule

3/three_tb.v
`timescale 1ns/1ns
`include "three.v"  
 
module three_tb();
reg A,B,C,D;
//Input
wire f;
//Output
three ex(A, B, C, D, f); 
initial
begin
	$dumpfile("three_tb.vcd");
	$dumpvars(0, three_tb);
	A=1'b0; B=1'b0; C=1'b0; D=1'b0; 
	#20;
	A=1'b0; B=1'b0; C=1'b0; D=1'b1;
	#20;
	A=1'b0; B=1'b0; C=1'b1; D=1'b0;
	#20;
	A=1'b0; B=1'b0; C=1'b1; D=1'b1;
	#20;
	A=1'b0; B=1'b1; C=1'b0; D=1'b0;
	#20;
	A=1'b0; B=1'b1; C=1'b0; D=1'b1;
	#20;
	A=1'b0; B=1'b1; C=1'b1; D=1'b0;
	#20;
	A=1'b0; B=1'b1; C=1'b1; D=1'b1;
	#20;
	A=1'b1; B=1'b0; C=1'b0; D=1'b0; 
	#20;
	A=1'b1; B=1'b0; C=1'b0; D=1'b1;
	#20;
	A=1'b1; B=1'b0; C=1'b1; D=1'b0;
	#20;
	A=1'b1; B=1'b0; C=1'b1; D=1'b1;
	#20;
	A=1'b1; B=1'b1; C=1'b0; D=1'b0;
	#20;
	A=1'b1; B=1'b1; C=1'b0; D=1'b1;
	#20;
	A=1'b1; B=1'b1; C=1'b1; D=1'b0;
	#20;
	A=1'b1; B=1'b1; C=1'b1; D=1'b1;
	#20;
	$display("Test complete");	
end
endmodule

3/three_tb.vcd
$date
	Thu Sep  8 10:26:24 2022
$end
$version
	Icarus Verilog
$end
$timescale
	1ns
$end
$scope module three_tb $end
$var wire 1 ! f $end
$var reg 1 " A $end
$var reg 1 # B $end
$var reg 1 $ C $end
$var reg 1 % D $end
$scope module ex $end
$var wire 1 " A $end
$var wire 1 # B $end
$var wire 1 $ C $end
$var wire 1 % D $end
$var wire 1 & a $end
$var wire 1 ' c $end
$var wire 1 ( d $end
$var wire 1 ! f $end
$var wire 1 ) l $end
$upscope $end
$upscope $end
$enddefinitions $end
#0
$dumpvars
0)
1(
1'
1&
0%
0$
0#
0"
0!
$end
#20
1!
0(
1%
#40
0!
1(
0'
0%
1$
#60
1!
0(
1%
#80
0!
1(
1'
0%
0$
1#
#100
1!
0(
1%
#120
0!
1(
0'
0%
1$
#140
1!
0(
1%
#160
0!
1(
1'
0&
0%
0$
0#
1"
#180
1!
0(
1%
#200
0!
1)
1(
0'
0%
1$
#220
0(
1%
#240
0)
1(
1'
0%
0$
1#
#260
1!
0(
1%
#280
0!
1)
1(
0'
0%
1$
#300
0(
1%
