Additional_1/first.v
module first(a,b,c,f1,f2);
	input a,b,c;
	output f1,f2;
	assign f1=(a&(~c))|(b&c)|((~b)&(~c));
	assign f2=(a|(~b)|c)&(a|b|(~c))&((~a)|b|(~c));
endmodule

Additional_1/first_tb.v
`timescale 1ns/1ns
`include "first.v"

module first_tb();
reg a,b,c;
wire f1,f2;

first ex(a,b,c,f1,f2);
initial
begin
	
	$dumpfile("first_tb.vcd");
	$dumpvars(0, first_tb);
	
	a=1'b0;b=1'b0;c=1'b0;
	#20;
	
	a=1'b0;b=1'b0;c=1'b1;
	#20;
	
	a=1'b0;b=1'b1;c=1'b0;
	#20;
	
	a=1'b0;b=1'b1;c=1'b1;
	#20;
	
	a=1'b1;b=1'b0;c=1'b0;
	#20;
	
	a=1'b1;b=1'b0;c=1'b1;
	#20;
	
	a=1'b1;b=1'b1;c=1'b0;
	#20;
	
	a=1'b1;b=1'b1;c=1'b1;
	#20;
	
	$display("Test complete");
end

endmodule

Additional_1/first_tb.vcd
$date
	Thu Aug 18 11:04:34 2022
$end
$version
	Icarus Verilog
$end
$timescale
	1ns
$end
$scope module first_tb $end
$var wire 1 ! f2 $end
$var wire 1 " f1 $end
$var reg 1 # a $end
$var reg 1 $ b $end
$var reg 1 % c $end
$scope module ex $end
$var wire 1 # a $end
$var wire 1 $ b $end
$var wire 1 % c $end
$var wire 1 " f1 $end
$var wire 1 ! f2 $end
$upscope $end
$upscope $end
$enddefinitions $end
#0
$dumpvars
0%
0$
0#
1"
1!
$end
#20
0!
0"
1%
#40
0!
0%
1$
#60
1"
1!
1%
#80
0%
0$
1#
#100
0"
0!
1%
#120
1"
1!
0%
1$
#140
1%
