6/three.v
module three(W, S, f);
	input [15:0]W;
	input [3:0]S;
	output f;
	mux8to1 M0(W[7:0], S[2:0], k);
	mux8to1 M1(W[15:8], S[2:0], l);
	mux2to1 M2(k, l, S[3], f);
endmodule

module mux8to1(W, S, f);
	input [7:0]W;
	input [2:0]S;
	output reg f;
	
	always @(W or S)
	begin
		case(S)
			3'b000: begin
				f=W[0];
				end
			3'b001: begin
				f=W[1];
			        end
			3'b010: begin
				f=W[2];
				end
			3'b011: begin
				f=W[3];
				end
			3'b100: begin
				f=W[4];
				end
			3'b101: begin
				f=W[5];
				end
			3'b110: begin
				f=W[6];
				end
			3'b111: begin
				f=W[7];
				end
		endcase
	end
endmodule

module mux2to1(w0, w1, s, f);
	input w0, w1, s;
	output reg f;
	
	always @(w0 or w1 or s)
	begin
		if (s==1)
			f=w1;
		else
			f=w0;
	end
endmodule

6/three_tb.v
`timescale 1ns/1ns
`include "three.v"

module three_tb();
reg [15:0]W;
reg [3:0]S;
wire f;

three ex(W, S, f);
initial
begin
	$dumpfile("three_tb.vcd");
	$dumpvars(0,three_tb);
	
	W=16'b0011001100110011;
	S=4'b0000; #20;
	S=4'b0001; #20;
	S=4'b0010; #20;
	S=4'b0011; #20;
	S=4'b0100; #20;
	S=4'b0101; #20;
	S=4'b0110; #20;
	S=4'b0111; #20;
	
	S=4'b1000; #20;
	S=4'b1001; #20;
	S=4'b1010; #20;
	S=4'b1011; #20;
	S=4'b1100; #20;
	S=4'b1101; #20;
	S=4'b1110; #20;
	S=4'b1111; #20;

	$display("test Complete");
end
endmodule

6/three_tb.vcd
$date
	Thu Oct  6 10:29:16 2022
$end
$version
	Icarus Verilog
$end
$timescale
	1ns
$end
$scope module three_tb $end
$var wire 1 ! f $end
$var reg 4 " S [3:0] $end
$var reg 16 # W [15:0] $end
$scope module ex $end
$var wire 4 $ S [3:0] $end
$var wire 16 % W [15:0] $end
$var wire 1 & l $end
$var wire 1 ' k $end
$var wire 1 ! f $end
$scope module M0 $end
$var wire 3 ( S [2:0] $end
$var wire 8 ) W [7:0] $end
$var reg 1 ' f $end
$upscope $end
$scope module M1 $end
$var wire 3 * S [2:0] $end
$var wire 8 + W [7:0] $end
$var reg 1 & f $end
$upscope $end
$scope module M2 $end
$var wire 1 , s $end
$var wire 1 ' w0 $end
$var wire 1 & w1 $end
$var reg 1 ! f $end
$upscope $end
$upscope $end
$upscope $end
$enddefinitions $end
#0
$dumpvars
0,
b110011 +
b0 *
b110011 )
b0 (
1'
1&
b11001100110011 %
b0 $
b11001100110011 #
b0 "
1!
$end
#20
b1 (
b1 *
b1 "
b1 $
#40
0!
0'
0&
b10 (
b10 *
b10 "
b10 $
#60
b11 (
b11 *
b11 "
b11 $
#80
1!
1'
1&
b100 (
b100 *
b100 "
b100 $
#100
b101 (
b101 *
b101 "
b101 $
#120
0!
0'
0&
b110 (
b110 *
b110 "
b110 $
#140
b111 (
b111 *
b111 "
b111 $
#160
1!
1'
1&
b0 (
b0 *
1,
b1000 "
b1000 $
#180
b1 (
b1 *
b1001 "
b1001 $
#200
0!
0'
0&
b10 (
b10 *
b1010 "
b1010 $
#220
b11 (
b11 *
b1011 "
b1011 $
#240
1!
1'
1&
b100 (
b100 *
b1100 "
b1100 $
#260
b101 (
b101 *
b1101 "
b1101 $
#280
0!
0'
0&
b110 (
b110 *
b1110 "
b1110 $
#300
b111 (
b111 *
b1111 "
b1111 $
