1/first.v
module first(a,b,c,d,f);
	input a,b,c,d;
	output f;
	and(e,a,b);
	or(g,e,c);
	not(h,g);
	and(i,h,d);

	and(j,a,b);
	or(k,c,j);
	or(l,d,k);
	
	and(f,i,l);
endmodule

1/first_tb.v
`timescale 1ns/1ns
`include "first.v"
 
module first_tb();
reg a,b,c,d;
//Input
wire f;
//Output
first ex2(a, b, c, d, f); //Instantiation of the module
initial
begin
	$dumpfile("first_tb.vcd");
	$dumpvars(0, first_tb);
	a=1'b0; b=1'b0; c=1'b0; d=1'b0; 
	#20;
	a=1'b0; b=1'b0; c=1'b0; d=1'b1;
	#20;
	a=1'b0; b=1'b0; c=1'b1; d=1'b0;
	#20;
	a=1'b0; b=1'b0; c=1'b1; d=1'b1;
	#20;
	a=1'b0; b=1'b1; c=1'b0; d=1'b0;
	#20;
	a=1'b0; b=1'b1; c=1'b0; d=1'b1;
	#20;
	a=1'b0; b=1'b1; c=1'b1; d=1'b0;
	#20;
	a=1'b0; b=1'b1; c=1'b1; d=1'b1;
	#20;
	a=1'b1; b=1'b0; c=1'b0; d=1'b0; 
	#20;
	a=1'b1; b=1'b0; c=1'b0; d=1'b1;
	#20;
	a=1'b1; b=1'b0; c=1'b1; d=1'b0;
	#20;
	a=1'b1; b=1'b0; c=1'b1; d=1'b1;
	#20;
	a=1'b1; b=1'b1; c=1'b0; d=1'b0;
	#20;
	a=1'b1; b=1'b1; c=1'b0; d=1'b1;
	#20;
	a=1'b1; b=1'b1; c=1'b1; d=1'b0;
	#20;
	a=1'b1; b=1'b1; c=1'b1; d=1'b1;
	#20;
	$display("Test complete");
end

endmodule

1/first_tb.vcd
$date
	Thu Aug 18 09:50:55 2022
$end
$version
	Icarus Verilog
$end
$timescale
	1ns
$end
$scope module first_tb $end
$var wire 1 ! f $end
$var reg 1 " a $end
$var reg 1 # b $end
$var reg 1 $ c $end
$var reg 1 % d $end
$scope module ex2 $end
$var wire 1 " a $end
$var wire 1 # b $end
$var wire 1 $ c $end
$var wire 1 % d $end
$var wire 1 & e $end
$var wire 1 ! f $end
$var wire 1 ' g $end
$var wire 1 ( h $end
$var wire 1 ) i $end
$var wire 1 * j $end
$var wire 1 + k $end
$var wire 1 , l $end
$upscope $end
$upscope $end
$enddefinitions $end
#0
$dumpvars
0,
0+
0*
0)
1(
0'
0&
0%
0$
0#
0"
0!
$end
#20
1!
1)
1,
1%
#40
0!
0(
0)
1'
1+
0%
1$
#60
1%
#80
1(
0,
0'
0+
0%
0$
1#
#100
1!
1)
1,
1%
#120
0!
0(
0)
1'
1+
0%
1$
#140
1%
#160
1(
0,
0'
0+
0%
0$
0#
1"
#180
1!
1)
1,
1%
#200
0!
0(
0)
1'
1+
0%
1$
#220
1%
#240
1&
1*
0%
0$
1#
#260
1%
#280
0%
1$
#300
1%
