1/second_ii.v
module second_ii(a,b,c,d,f,g);
	input a,b,c,d;
	output f,g;
	assign f=(~(a&b))^c^d;
	assign g=~(b|c|d);
endmodule

1/second_ii_tb.v
`timescale 1ns/1ns
`include "second_ii.v"
 
module second_ii_tb();
reg a,b,c,d;
//Input
wire f,g;
//Output
second_ii ex2(a, b, c, d, f, g); //Instantiation of the module
initial
begin
	$dumpfile("second_ii_tb.vcd");
	$dumpvars(0, second_ii_tb);
	a=1'b0; b=1'b0; c=1'b0; d=1'b0; 
	#20;
	a=1'b0; b=1'b0; c=1'b0; d=1'b1;
	#20;
	a=1'b0; b=1'b0; c=1'b1; d=1'b0;
	#20;
	a=1'b0; b=1'b0; c=1'b1; d=1'b1;
	#20;
	a=1'b0; b=1'b1; c=1'b0; d=1'b0;
	#20;
	a=1'b0; b=1'b1; c=1'b0; d=1'b1;
	#20;
	a=1'b0; b=1'b1; c=1'b1; d=1'b0;
	#20;
	a=1'b0; b=1'b1; c=1'b1; d=1'b1;
	#20;
	a=1'b1; b=1'b0; c=1'b0; d=1'b0; 
	#20;
	a=1'b1; b=1'b0; c=1'b0; d=1'b1;
	#20;
	a=1'b1; b=1'b0; c=1'b1; d=1'b0;
	#20;
	a=1'b1; b=1'b0; c=1'b1; d=1'b1;
	#20;
	a=1'b1; b=1'b1; c=1'b0; d=1'b0;
	#20;
	a=1'b1; b=1'b1; c=1'b0; d=1'b1;
	#20;
	a=1'b1; b=1'b1; c=1'b1; d=1'b0;
	#20;
	a=1'b1; b=1'b1; c=1'b1; d=1'b1;
	#20;
	$display("Test complete");
end

endmodule

1/second_ii_tb.vcd
$date
	Thu Aug 18 10:39:25 2022
$end
$version
	Icarus Verilog
$end
$timescale
	1ns
$end
$scope module second_ii_tb $end
$var wire 1 ! g $end
$var wire 1 " f $end
$var reg 1 # a $end
$var reg 1 $ b $end
$var reg 1 % c $end
$var reg 1 & d $end
$scope module ex2 $end
$var wire 1 # a $end
$var wire 1 $ b $end
$var wire 1 % c $end
$var wire 1 & d $end
$var wire 1 " f $end
$var wire 1 ! g $end
$upscope $end
$upscope $end
$enddefinitions $end
#0
$dumpvars
0&
0%
0$
0#
1"
1!
$end
#20
0!
0"
1&
#40
0&
1%
#60
1"
1&
#80
0&
0%
1$
#100
0"
1&
#120
0&
1%
#140
1"
1&
#160
1!
0&
0%
0$
1#
#180
0!
0"
1&
#200
0&
1%
#220
1"
1&
#240
0"
0&
0%
1$
#260
1"
1&
#280
0&
1%
#300
0"
1&
