8/four.v
module four(W, Y, z);
	input [3:0]W;
	output reg z;
	output reg [1:0]Y;
	always @(*)
	begin
		z=1;
		casex(W)
			4'bxxx1: Y=0;
			4'bxx10: Y=1;
			4'bx100: Y=2;
			4'b1000: Y=3;
			default: begin
					z=0;
					Y=2'bxx;
				 end					
		endcase   			 
	end	
endmodule

8/five_tb.v
`include "four.v"

module four_tb();
reg [3:0]W;
wire z;
wire [1:0]Y;

four ex(W, Y, z);
initial
begin
	$dumpfile("four_tb.vcd");
	$dumpvars(0,four_tb);
	
	W=4'b0001; #20;
	W=4'b0010; #20;
	W=4'b0011; #20;
	W=4'b0100; #20;
	W=4'b0101; #20;
	W=4'b0110; #20;
	W=4'b0111; #20;
	W=4'b1000; #20;
	W=4'b1001; #20;
	W=4'b1010; #20;
	W=4'b1011; #20;
	W=4'b1100; #20;
	W=4'b1101; #20;
	W=4'b1110; #20;
	W=4'b1111; #20;
	W=4'b0000; #20;
	
	$display("test Complete");
end
endmodule

8/four_tb.vcd
$date
	Thu Oct 20 11:16:33 2022
$end
$version
	Icarus Verilog
$end
$timescale
	1s
$end
$scope module four_tb $end
$var wire 1 ! z $end
$var wire 2 " Y [1:0] $end
$var reg 4 # W [3:0] $end
$scope module ex $end
$var wire 4 $ W [3:0] $end
$var reg 2 % Y [1:0] $end
$var reg 1 ! z $end
$upscope $end
$upscope $end
$enddefinitions $end
#0
$dumpvars
b0 %
b1 $
b1 #
b0 "
1!
$end
#20
b1 "
b1 %
b10 #
b10 $
#40
b0 "
b0 %
b11 #
b11 $
#60
b10 "
b10 %
b100 #
b100 $
#80
b0 "
b0 %
b101 #
b101 $
#100
b1 "
b1 %
b110 #
b110 $
#120
b0 "
b0 %
b111 #
b111 $
#140
b11 "
b11 %
b1000 #
b1000 $
#160
b0 "
b0 %
b1001 #
b1001 $
#180
b1 "
b1 %
b1010 #
b1010 $
#200
b0 "
b0 %
b1011 #
b1011 $
#220
b10 "
b10 %
b1100 #
b1100 $
#240
b0 "
b0 %
b1101 #
b1101 $
#260
b1 "
b1 %
b1110 #
b1110 $
#280
b0 "
b0 %
b1111 #
b1111 $
#300
bx "
bx %
0!
b0 #
b0 $
