8/two.v
module two(En, W, Y);
	input [3:0]W;
	input En;
	output [0:15]Y;
	not(a,W[3]);
	and(e0,a,En);
	and(e1,W[3],En);
	decoder3t8 D0(e0, W[2:0],Y[0:7]);
	decoder3t8 D1(e1, W[2:0],Y[8:15]);
endmodule

module decoder3t8(En, W, Y);
	input [2:0]W;
	input En;
	output reg [0:7]Y; 
	integer k;
	always @(*)
	begin
		Y=8'b00000000;
		for (k = 0; k <= 7; k = k+1)
			if ((W == k) && (En == 1))
				Y[k] = 1;   			 
	end
endmodule

8/two_tb.v
`timescale 1ns/1ns
`include "two.v"

module two_tb();
reg [3:0]W;
reg En;
wire [0:15]Y;

two ex(En, W, Y);
initial
begin
	$dumpfile("two_tb.vcd");
	$dumpvars(0,two_tb);
	
	En=1'b1;
	W=4'b0000; #20;
	W=4'b0001; #20;
	W=4'b0010; #20;
	W=4'b0011; #20;
	W=4'b0100; #20;
	W=4'b0101; #20;
	W=4'b0110; #20;
	W=4'b0111; #20;
	W=4'b1000; #20;
	W=4'b1001; #20;
	W=4'b1010; #20;
	W=4'b1011; #20;
	W=4'b1100; #20;
	W=4'b1101; #20;
	W=4'b1110; #20;
	W=4'b1111; #20;
	
	En=1'b0; W=4'b1001; #20;

	
	$display("test Complete");
end
endmodule

8/two_tb.vcd
$date
	Thu Oct 20 10:34:32 2022
$end
$version
	Icarus Verilog
$end
$timescale
	1ns
$end
$scope module two_tb $end
$var wire 16 ! Y [0:15] $end
$var reg 1 " En $end
$var reg 4 # W [3:0] $end
$scope module ex $end
$var wire 1 " En $end
$var wire 4 $ W [3:0] $end
$var wire 1 % a $end
$var wire 1 & e0 $end
$var wire 1 ' e1 $end
$var wire 16 ( Y [0:15] $end
$scope module D0 $end
$var wire 1 & En $end
$var wire 3 ) W [2:0] $end
$var reg 8 * Y [0:7] $end
$var integer 32 + k [31:0] $end
$upscope $end
$scope module D1 $end
$var wire 1 ' En $end
$var wire 3 , W [2:0] $end
$var reg 8 - Y [0:7] $end
$var integer 32 . k [31:0] $end
$upscope $end
$upscope $end
$upscope $end
$enddefinitions $end
#0
$dumpvars
b1000 .
b0 -
b0 ,
b1000 +
b10000000 *
b0 )
b1000000000000000 (
0'
1&
1%
b0 $
b0 #
1"
b1000000000000000 !
$end
#20
b1000 +
b100000000000000 !
b100000000000000 (
b1000000 *
b1000 .
b1 )
b1 ,
b1 #
b1 $
#40
b1000 +
b10000000000000 !
b10000000000000 (
b100000 *
b1000 .
b10 )
b10 ,
b10 #
b10 $
#60
b1000 +
b1000000000000 !
b1000000000000 (
b10000 *
b1000 .
b11 )
b11 ,
b11 #
b11 $
#80
b1000 +
b100000000000 !
b100000000000 (
b1000 *
b1000 .
b100 )
b100 ,
b100 #
b100 $
#100
b1000 +
b10000000000 !
b10000000000 (
b100 *
b1000 .
b101 )
b101 ,
b101 #
b101 $
#120
b1000 +
b1000000000 !
b1000000000 (
b10 *
b1000 .
b110 )
b110 ,
b110 #
b110 $
#140
b1000 +
b100000000 !
b100000000 (
b1 *
b1000 .
b111 )
b111 ,
b111 #
b111 $
#160
0&
b10000000 -
0%
1'
b1000 +
b10000000 !
b10000000 (
b0 *
b1000 .
b0 )
b0 ,
b1000 #
b1000 $
#180
b1000 +
b1000 .
b1000000 !
b1000000 (
b1000000 -
b1 )
b1 ,
b1001 #
b1001 $
#200
b1000 +
b1000 .
b100000 !
b100000 (
b100000 -
b10 )
b10 ,
b1010 #
b1010 $
#220
b1000 +
b1000 .
b10000 !
b10000 (
b10000 -
b11 )
b11 ,
b1011 #
b1011 $
#240
b1000 +
b1000 .
b1000 !
b1000 (
b1000 -
b100 )
b100 ,
b1100 #
b1100 $
#260
b1000 +
b1000 .
b100 !
b100 (
b100 -
b101 )
b101 ,
b1101 #
b1101 $
#280
b1000 +
b1000 .
b10 !
b10 (
b10 -
b110 )
b110 ,
b1110 #
b1110 $
#300
b1000 +
b1000 .
b1 !
b1 (
b1 -
b111 )
b111 ,
b1111 #
b1111 $
#320
b1000 +
b1000 .
b0 !
b0 (
b0 -
b1 )
b1 ,
0'
b1001 #
b1001 $
0"
