2/two_b.v
module two_b(A, B, C, D,f);
	input A, B, C, D;
	output f;
	
	assign f=(~A|B|~D)&(~A|B|~C)&(A|~B|D)&(~B|C|D);
endmodule

2/two_b_tb.v
`timescale 1ns/1ns
`include "two_b.v"  //two_b in 2b
 
module two_b_tb();
reg A,B,C,D;
//Input
wire f;
//Output
two_b ex(A, B, C, D, f); //two_b in 2b
initial
begin
	$dumpfile("two_b_tb.vcd");
	$dumpvars(0, two_b_tb);
	A=1'b0; B=1'b0; C=1'b0; D=1'b0; 
	#20;
	A=1'b0; B=1'b0; C=1'b0; D=1'b1;
	#20; 
	A=1'b0; B=1'b0; C=1'b1; D=1'b0;
	#20;
	A=1'b0; B=1'b0; C=1'b1; D=1'b1;
	#20;
	A=1'b0; B=1'b1; C=1'b0; D=1'b0;
	#20;
	A=1'b0; B=1'b1; C=1'b0; D=1'b1;
	#20;
	A=1'b0; B=1'b1; C=1'b1; D=1'b0;
	#20;
	A=1'b0; B=1'b1; C=1'b1; D=1'b1;
	#20;
	A=1'b1; B=1'b0; C=1'b0; D=1'b0; 
	#20;
	A=1'b1; B=1'b0; C=1'b0; D=1'b1;
	#20;
	A=1'b1; B=1'b0; C=1'b1; D=1'b0;
	#20;
	A=1'b1; B=1'b0; C=1'b1; D=1'b1;
	#20;
	A=1'b1; B=1'b1; C=1'b0; D=1'b0;
	#20;
	A=1'b1; B=1'b1; C=1'b0; D=1'b1;
	#20;
	A=1'b1; B=1'b1; C=1'b1; D=1'b0;
	#20;
	A=1'b1; B=1'b1; C=1'b1; D=1'b1;
	#20;
	$display("Test complete");
end

endmodule

2/two_b_tb.vcd
$date
	Thu Sep  1 10:10:23 2022
$end
$version
	Icarus Verilog
$end
$timescale
	1ns
$end
$scope module two_b_tb $end
$var wire 1 ! f $end
$var reg 1 " A $end
$var reg 1 # B $end
$var reg 1 $ C $end
$var reg 1 % D $end
$scope module ex $end
$var wire 1 " A $end
$var wire 1 # B $end
$var wire 1 $ C $end
$var wire 1 % D $end
$var wire 1 ! f $end
$upscope $end
$upscope $end
$enddefinitions $end
#0
$dumpvars
0%
0$
0#
0"
1!
$end
#20
1%
#40
0%
1$
#60
1%
#80
0!
0%
0$
1#
#100
1!
1%
#120
0!
0%
1$
#140
1!
1%
#160
0%
0$
0#
1"
#180
0!
1%
#200
0%
1$
#220
1%
#240
0%
0$
1#
#260
1!
1%
#280
0%
1$
#300
1%
